README.md
setup.py
alice_scripts/__init__.py
alice_scripts/modifiers.py
alice_scripts/requests.py
alice_scripts/say.py
alice_scripts/skill.py
alice_scripts.egg-info/PKG-INFO
alice_scripts.egg-info/SOURCES.txt
alice_scripts.egg-info/dependency_links.txt
alice_scripts.egg-info/requires.txt
alice_scripts.egg-info/top_level.txt