Metadata-Version: 1.1
Name: alice-scripts
Version: 0.2.post1
Summary: Simple way to create complex scripts for Yandex.Alice
Home-page: http://github.com/borzunov/alice_scripts
Author: Alexander Borzunov
Author-email: borzunov.alexander@gmail.com
License: MIT
Keywords: yandex-alice
Platform: UNKNOWN
Classifier: Development Status :: 4 - Beta
Classifier: Environment :: Console
Classifier: Framework :: AsyncIO
Classifier: Intended Audience :: Developers
Classifier: Intended Audience :: System Administrators
Classifier: License :: OSI Approved :: MIT License
Classifier: Operating System :: OS Independent
Classifier: Programming Language :: Python
Classifier: Topic :: Software Development :: Libraries :: Application Frameworks
